xunfei/__init__.py
xunfei/spark/__init__.py
xunfei/spark/client.py
xunfei/spark/response.py
xunfei_spark_python-0.1.0.dist-info/METADATA
xunfei_spark_python-0.1.0.dist-info/WHEEL
xunfei_spark_python-0.1.0.dist-info/top_level.txt
xunfei_spark_python-0.1.0.dist-info/RECORD
