Metadata-Version: 2.1
Name: xunfei-spark-python
Version: 0.1.0
Summary: 科大讯飞星火大模型SDK
Home-page: https://github.com/sunmh207/xunfei-spark-python
Author: Stanley Sun
Author-email: stanley.java@gmail.com
License: MIT
Classifier: License :: OSI Approved :: MIT License
Classifier: Programming Language :: Python
Classifier: Programming Language :: Python :: 3
Classifier: Programming Language :: Python :: 3.10
Classifier: Programming Language :: Python :: Implementation :: CPython
Classifier: Programming Language :: Python :: Implementation :: PyPy
Requires-Python: >=3.7.0
Requires-Dist: websocket-client ==1.7.0
